symbl/AuthenticationToken.py
symbl/Connection.py
symbl/Conversations.py
symbl/__init__.py
symbl/callScore.py
symbl/async_api/Audio.py
symbl/async_api/Text.py
symbl/async_api/Video.py
symbl/async_api/__init__.py
symbl/configs/__init__.py
symbl/configs/configs.py
symbl/conversations_api/ConversationsApi.py
symbl/conversations_api/__init__.py
symbl/jobs_api/Job.py
symbl/jobs_api/JobStatus.py
symbl/jobs_api/__init__.py
symbl/streaming_api/StreamingApi.py
symbl/streaming_api/StreamingConnection.py
symbl/streaming_api/__init__.py
symbl/telephony_api/TelephonyApi.py
symbl/telephony_api/TelephonyValidators.py
symbl/telephony_api/__init__.py
symbl/utils/Decorators.py
symbl/utils/Helper.py
symbl/utils/Logger.py
symbl/utils/Threads.py
symbl/utils/__init__.py
tests/__init__.py
tests/audio_test.py
tests/authentication_token_test.py
tests/conversations_api_test.py
tests/conversations_test.py
tests/telephony_test.py
tests/text_test.py
tests/video_test.py
symbl-2.0.6.dist-info/LICENSE
symbl-2.0.6.dist-info/METADATA
symbl-2.0.6.dist-info/WHEEL
symbl-2.0.6.dist-info/top_level.txt
symbl-2.0.6.dist-info/RECORD
