Metadata-Version: 2.1
Name: symbl
Version: 2.0.6
Summary: symbl.ai SDK
Home-page: 
Author-email: info@symbl.ai
Keywords: Symbl.ai SDK
License-File: LICENSE
Requires-Dist: symbl-rest >=1.0.14
Requires-Dist: websocket-client >=0.59.0
Requires-Dist: pyaudio ~=0.2.12
Requires-Dist: numpy
